xhlog/__init__.py
xhlog-0.0.3.dist-info/LICENSE
xhlog-0.0.3.dist-info/METADATA
xhlog-0.0.3.dist-info/WHEEL
xhlog-0.0.3.dist-info/RECORD
